qatch/__init__.py
qatch/connectors/__init__.py
qatch/connectors/base_connector.py
qatch/connectors/sqlite_connector.py
qatch/connectors/utils.py
qatch/evaluate_dataset/__init__.py
qatch/evaluate_dataset/metrics_evaluators/__init__.py
qatch/evaluate_dataset/metrics_evaluators/base_evaluator.py
qatch/evaluate_dataset/metrics_evaluators/cell_precision.py
qatch/evaluate_dataset/metrics_evaluators/cell_recall.py
qatch/evaluate_dataset/metrics_evaluators/execution_accuracy.py
qatch/evaluate_dataset/metrics_evaluators/tuple_cardinality.py
qatch/evaluate_dataset/metrics_evaluators/tuple_constraint.py
qatch/evaluate_dataset/metrics_evaluators/tuple_order.py
qatch/evaluate_dataset/metrics_evaluators/utils.py
qatch/evaluate_dataset/metrics_evaluators/valid_efficiency_score.py
qatch/evaluate_dataset/orchestrator_evaluator.py
qatch/evaluate_dataset/state_orchestrator_evaluator.py
qatch/generate_dataset/__init__.py
qatch/generate_dataset/checklist_generators/__init__.py
qatch/generate_dataset/checklist_generators/base_generator.py
qatch/generate_dataset/checklist_generators/distinct_generator.py
qatch/generate_dataset/checklist_generators/groupby_generator.py
qatch/generate_dataset/checklist_generators/having_generator.py
qatch/generate_dataset/checklist_generators/join_generator.py
qatch/generate_dataset/checklist_generators/many_to_many_generator.py
qatch/generate_dataset/checklist_generators/null_generator.py
qatch/generate_dataset/checklist_generators/orderby_generator.py
qatch/generate_dataset/checklist_generators/project_generator.py
qatch/generate_dataset/checklist_generators/select_generator.py
qatch/generate_dataset/checklist_generators/simple_agg_generator.py
qatch/generate_dataset/checklist_generators/utils.py
qatch/generate_dataset/orchestrator_generator.py
qatch/generate_dataset/state_orchestrator_generator.py
qatch-1.0.36.dist-info/LICENSE
qatch-1.0.36.dist-info/METADATA
qatch-1.0.36.dist-info/WHEEL
qatch-1.0.36.dist-info/RECORD
