Metadata-Version: 2.1
Name: qatch
Version: 1.0.36
Summary: 
License: Apache-2.0
Author: spapicchio
Author-email: simone.papicchio@polito.it
Requires-Python: >=3.9,<4.0
Classifier: License :: OSI Approved :: Apache Software License
Classifier: Programming Language :: Python :: 3
Classifier: Programming Language :: Python :: 3.9
Classifier: Programming Language :: Python :: 3.10
Classifier: Programming Language :: Python :: 3.11
Classifier: Programming Language :: Python :: 3.12
Requires-Dist: eval-type-backport (>=0.2.0,<0.3.0)
Requires-Dist: func-timeout (>=4.3.5,<5.0.0)
Requires-Dist: langchain (>=0.3.9,<0.4.0)
Requires-Dist: langgraph (>=0.4,<0.5)
Requires-Dist: notebook (>=7.3.3,<8.0.0)
Requires-Dist: pandas (>=2,<3)
Requires-Dist: sqlalchemy (>=2.0.36,<3.0.0)
Requires-Dist: tqdm (>=4.66.1,<5.0.0)
